cairo_rs_py-0.2.0.dist-info/METADATA
cairo_rs_py-0.2.0.dist-info/WHEEL
cairo_rs_py-0.2.0.dist-info/license_files/LICENSE
cairo_rs_py/__init__.py
cairo_rs_py/cairo_rs_py.cpython-39-darwin.so
cairo_rs_py-0.2.0.dist-info/RECORD
